.testr.conf
AUTHORS
AUTHORS~
ChangeLog
LICENSE
MANIFEST.in
README.md
README.rst
requirements.txt
setup.cfg
setup.py
python_stacktaskclient.egg-info/PKG-INFO
python_stacktaskclient.egg-info/SOURCES.txt
python_stacktaskclient.egg-info/dependency_links.txt
python_stacktaskclient.egg-info/entry_points.txt
python_stacktaskclient.egg-info/not-zip-safe
python_stacktaskclient.egg-info/pbr.json
python_stacktaskclient.egg-info/requires.txt
python_stacktaskclient.egg-info/top_level.txt
stacktaskclient/__init__.py
stacktaskclient/client.py
stacktaskclient/exc.py
stacktaskclient/shell.py
stacktaskclient/common/__init__.py
stacktaskclient/common/http.py
stacktaskclient/common/utils.py
stacktaskclient/openstack/__init__.py
stacktaskclient/openstack/common/__init__.py
stacktaskclient/openstack/common/_i18n.py
stacktaskclient/openstack/common/cliutils.py
stacktaskclient/openstack/common/apiclient/__init__.py
stacktaskclient/openstack/common/apiclient/auth.py
stacktaskclient/openstack/common/apiclient/base.py
stacktaskclient/openstack/common/apiclient/client.py
stacktaskclient/openstack/common/apiclient/exceptions.py
stacktaskclient/openstack/common/apiclient/fake_client.py
stacktaskclient/openstack/common/apiclient/utils.py
stacktaskclient/osc/__init__.py
stacktaskclient/osc/plugin.py
stacktaskclient/osc/v1/__init__.py
stacktaskclient/osc/v1/notifications.py
stacktaskclient/osc/v1/signup.py
stacktaskclient/osc/v1/status.py
stacktaskclient/osc/v1/tasks.py
stacktaskclient/osc/v1/tokens.py
stacktaskclient/osc/v1/users.py
stacktaskclient/v1/__init__.py
stacktaskclient/v1/build_info.py
stacktaskclient/v1/client.py
stacktaskclient/v1/notifications.py
stacktaskclient/v1/roles.py
stacktaskclient/v1/shell.py
stacktaskclient/v1/signup.py
stacktaskclient/v1/status.py
stacktaskclient/v1/tasks.py
stacktaskclient/v1/tokens.py
stacktaskclient/v1/users.py