Metadata-Version: 1.1
Name: python-stacktaskclient
Version: 0.1.6
Summary: StackTask API Client Library
Home-page: https://github.com/catalyst/stacktask-client
Author: Dale Smith
Author-email: dale@catalyst-eu.net
License: UNKNOWN
Platform: UNKNOWN
Classifier: Environment :: OpenStack
Classifier: Intended Audience :: Information Technology
Classifier: Intended Audience :: System Administrators
Classifier: License :: OSI Approved :: Apache Software License
Classifier: Operating System :: POSIX :: Linux
Classifier: Programming Language :: Python
Classifier: Programming Language :: Python :: 2
Classifier: Programming Language :: Python :: 2.7
Classifier: Programming Language :: Python :: 2.6
